trajminer/__init__.py
trajminer/trajectory_data.py
trajminer/classification/__init__.py
trajminer/classification/base.py
trajminer/classification/knn.py
trajminer/classification/movelets.py
trajminer/classification/traclass.py
trajminer/clustering/__init__.py
trajminer/clustering/agglomerative.py
trajminer/clustering/base.py
trajminer/clustering/density.py
trajminer/clustering/kmedoids.py
trajminer/preprocessing/__init__.py
trajminer/preprocessing/filter.py
trajminer/preprocessing/one_hot.py
trajminer/preprocessing/segmentation.py
trajminer/similarity/__init__.py
trajminer/similarity/base.py
trajminer/similarity/classes.py
trajminer/similarity/pairwise.py
trajminer/tests/__init__.py
trajminer/tests/test_segmentation.py
trajminer/utils/__init__.py
trajminer/utils/geohash.py
trajminer/utils/loader.py
trajminer/utils/distance/__init__.py
trajminer/utils/distance/functions.py
trajminer-0.1.0a1.dist-info/DESCRIPTION.rst
trajminer-0.1.0a1.dist-info/METADATA
trajminer-0.1.0a1.dist-info/RECORD
trajminer-0.1.0a1.dist-info/WHEEL
trajminer-0.1.0a1.dist-info/metadata.json
trajminer-0.1.0a1.dist-info/top_level.txt
