Metadata-Version: 2.0
Name: trajminer
Version: 0.1.0a1
Summary: A trajectory mining library
Home-page: https://trajminer.github.io/
License: UNKNOWN
Keywords: trajectory mining
Platform: UNKNOWN
Classifier: Development Status :: 2 - Pre-Alpha
Classifier: Intended Audience :: Science/Research
Classifier: Intended Audience :: Developers
Classifier: Topic :: Scientific/Engineering
Classifier: Topic :: Software Development :: Libraries
Classifier: Operating System :: POSIX :: Linux
Classifier: Programming Language :: Python :: 3
Classifier: License :: OSI Approved :: MIT License
Requires-Dist: joblib (>=0.13.0)
Requires-Dist: numpy (>=1.15.3)
Requires-Dist: scikit-learn (>=0.19.1)
Requires-Dist: keras (>=2.2.4)
Requires-Dist: geohash2 (>=1.1)
